<?xml version="1.0" encoding="UTF-8" standalone="no"?>
<!DOCTYPE properties SYSTEM "http://java.sun.com/dtd/properties.dtd">
<properties>
<comment>Gaalop Configuration File</comment>
<entry key="de.gaalop.clucalc.output.Plugin.suffix">_opt</entry>
<entry key="de.gaalop.maple.Plugin.constantFolding">false</entry>
<entry key="de.gaalop.maple.Plugin.gaalopPath">gaalopCA_4_1.m</entry>
<entry key="de.gaalop.cpp.Plugin.standalone">true</entry>
<entry key="de.gaalop.gaalet.output.Plugin.useNameTable">true</entry>
<entry key="de.gaalop.maple.Plugin.mapleBinaryPath">/net/bifur/gaalop/maple/bin.IBM_INTEL_LINUX/</entry>
<entry key="de.gaalop.maple.Plugin.mapleJavaPath">/net/bifur/gaalop/maple/java/</entry>
</properties>
